wiredrss/__init__.py
wiredrss/wiredrss.py
wiredrss-0.1.2.dist-info/METADATA
wiredrss-0.1.2.dist-info/WHEEL
wiredrss-0.1.2.dist-info/top_level.txt
wiredrss-0.1.2.dist-info/RECORD
