Metadata-Version: 2.4
Name: wiredrss
Version: 0.1.2
Summary: Typed helper for consuming WIRED’s RSS feed.
Requires-Python: >=3.11
Requires-Dist: feedparser>=6.0
